clipreplace/__init__.py
clipreplace/__main__.py
clipreplace/py.typed
clipreplace-0.1.5.dist-info/METADATA
clipreplace-0.1.5.dist-info/WHEEL
clipreplace-0.1.5.dist-info/entry_points.txt
clipreplace-0.1.5.dist-info/licenses/LICENSE
clipreplace-0.1.5.dist-info/RECORD
