Metadata-Version: 2.4
Name: clipreplace
Version: 0.1.5
Summary: Replace a section of text in a file with clipboard content.
Project-URL: Homepage, https://github.com/l-lumin/clipreplace
Project-URL: Issues, https://github.com/l-lumin/clipreplace/issues
Author: Vu Bao Long
License-File: LICENSE
Classifier: License :: OSI Approved :: MIT License
Classifier: Operating System :: OS Independent
Classifier: Programming Language :: Python :: 3
Requires-Python: >=3.8
Requires-Dist: pyperclip>=1.9.0
